Metadata-Version: 1.0
Name: udacityMLEdistributions
Version: 0.57
Summary: Gaussian distributions
Home-page: UNKNOWN
Author: UNKNOWN
Author-email: UNKNOWN
License: UNKNOWN
Platform: UNKNOWN
